ansible_observe/opentelemetry/apps.py
ansible_observe/opentelemetry/instrument.py
django_ansible_observability-0.1.5.dist-info/METADATA
django_ansible_observability-0.1.5.dist-info/WHEEL
django_ansible_observability-0.1.5.dist-info/top_level.txt
django_ansible_observability-0.1.5.dist-info/RECORD
