Metadata-Version: 2.4
Name: django-ansible-observability
Version: 0.1.5
Summary: Django application for Ansible observability with OpenTelemetry integration
Author-email: Chris Meyers <chris.meyers.fsu@gmail.com>
License: MIT
Project-URL: Homepage, https://github.com/chrismeyersfsu/django-ansible-observability
Project-URL: Repository, https://github.com/chrismeyersfsu/django-ansible-observability
Project-URL: Issues, https://github.com/chrismeyersfsu/django-ansible-observability/issues
Classifier: Development Status :: 3 - Alpha
Classifier: Framework :: Django
Classifier: Framework :: Django :: 4.2
Classifier: Intended Audience :: Developers
Classifier: License :: OSI Approved :: MIT License
Classifier: Operating System :: OS Independent
Classifier: Programming Language :: Python :: 3
Classifier: Programming Language :: Python :: 3.8
Classifier: Programming Language :: Python :: 3.9
Classifier: Programming Language :: Python :: 3.10
Classifier: Programming Language :: Python :: 3.11
Classifier: Programming Language :: Python :: 3.12
Classifier: Topic :: Software Development :: Libraries :: Python Modules
Classifier: Topic :: System :: Monitoring
Requires-Python: >=3.8
Requires-Dist: Django<4.3.0,>=4.2.21
Requires-Dist: opentelemetry-api
Requires-Dist: opentelemetry-sdk
Requires-Dist: opentelemetry-instrumentation-django
Requires-Dist: opentelemetry-instrumentation-grpc
Requires-Dist: opentelemetry-instrumentation-logging
Requires-Dist: opentelemetry-instrumentation-psycopg
Requires-Dist: opentelemetry-instrumentation-psycopg2
Requires-Dist: opentelemetry-instrumentation-requests
Requires-Dist: opentelemetry-exporter-otlp-proto-grpc
Requires-Dist: opentelemetry-exporter-richconsole
Requires-Dist: requests
Requires-Dist: psycopg
Provides-Extra: dev
Requires-Dist: pytest; extra == "dev"
Requires-Dist: pytest-django; extra == "dev"
Requires-Dist: black; extra == "dev"
Requires-Dist: flake8; extra == "dev"
Requires-Dist: mypy; extra == "dev"
Provides-Extra: psycopg2
Requires-Dist: psycopg2; extra == "psycopg2"
